{
  "gitSyncId": "68b68debccdbe80c87356bca_301d2048-6b3c-4bdb-9894-c55dbe2c8c0f",
  "id": "OnePage_users_starts_with_M",
  "pluginId": "postgres-plugin",
  "pluginType": "DB",
  "unpublishedAction": {
    "actionConfiguration": {
      "body": "SELECT * FROM public.\"users\" WHERE name LIKE 'M%' LIMIT 10;",
      "encodeParamsToggle": true,
      "paginationType": "NONE",
      "pluginSpecifiedTemplates": [
        {
          "value": true
        }
      ],
      "timeoutInMillisecond": 10000
    },
    "confirmBeforeExecute": false,
    "datasource": {
      "id": "users",
      "isAutoGenerated": false,
      "name": "users",
      "pluginId": "postgres-plugin"
    },
    "dynamicBindingPathList": [],
    "name": "users_starts_with_M",
    "pageId": "OnePage",
    "runBehaviour": "MANUAL",
    "userSetOnLoad": false
  }
}